q2rad/__init__.py
q2rad/__main__.py
q2rad/locale/de/de.po
q2rad/locale/de/de.po~
q2rad/locale/de/LC_MESSAGES/q2rad.mo
q2rad/locale/q2rad.pot
q2rad/locale/ru/LC_MESSAGES/q2rad.mo
q2rad/locale/ru/ru.po
q2rad/locale/ru/ru.po~
q2rad/q2actions.py
q2rad/q2appmanager.py
q2rad/q2appselector.py
q2rad/q2constants.py
q2rad/q2extensions.py
q2rad/q2forms.py
q2rad/q2i18n.py
q2rad/q2lines.py
q2rad/q2make.py
q2rad/q2market.py
q2rad/q2modules.py
q2rad/q2packages.py
q2rad/q2queries.py
q2rad/q2rad.py
q2rad/q2raddb.py
q2rad/q2reports.py
q2rad/q2stylesettings.py
q2rad/q2utils.py
q2rad/version.py
q2rad-0.1.258.dist-info/entry_points.txt
q2rad-0.1.258.dist-info/LICENSE
q2rad-0.1.258.dist-info/METADATA
q2rad-0.1.258.dist-info/WHEEL
q2rad-0.1.258.dist-info/RECORD
