Metadata-Version: 2.1
Name: q2rad
Version: 0.1.258
Summary: RAD - database, GUI, reports
Author: Andrei Puchko
Author-email: andrei.puchko@gmx.de
Requires-Python: >=3.8.1,<4.0
Classifier: Programming Language :: Python :: 3
Classifier: Programming Language :: Python :: 3.9
Classifier: Programming Language :: Python :: 3.10
Classifier: Programming Language :: Python :: 3.11
Requires-Dist: packaging (>=24.0,<25.0)
Requires-Dist: q2data2docx (>=0.1.4,<0.2.0)
Requires-Dist: q2db (>=0.1.9,<0.2.0)
Requires-Dist: q2gui (>=0.1.36,<0.2.0)
Requires-Dist: q2report (>=0.1.16,<0.2.0)
Requires-Dist: q2terminal (>=0.1.10,<0.2.0)
